configlib/__init__.py
configlib/exceptions.py
configlib/finding/__init__.py
configlib/finding/_variations.py
configlib/finding/default_places.py
configlib/finding/find.py
configlib/finding/places.py
configlib/interface/__init__.py
configlib/interface/cls.py
configlib/interface/typing.py
configlib/interface/util.py
configlib/loading/__init__.py
configlib/loading/registry.py
configlib/loading/environ/__init__.py
configlib/loading/environ/loader.py
configlib/loading/environ/util.py
configlib/loading/loaders/__init__.py
configlib/loading/loaders/conf_loader.py
configlib/loading/loaders/dotenv_loader.py
configlib/loading/loaders/json5_loader.py
configlib/loading/loaders/json_loader.py
configlib/loading/loaders/jsonc_loader.py
configlib/loading/loaders/toml_loader.py
configlib/loading/loaders/xml_loader.py
configlib/loading/loaders/yaml_loader.py
configlib/util/__init__.py
configlib/util/get_any.py
configlib/validation/__init__.py
config_library-0.18.1.dist-info/LICENSE
config_library-0.18.1.dist-info/METADATA
config_library-0.18.1.dist-info/WHEEL
config_library-0.18.1.dist-info/top_level.txt
config_library-0.18.1.dist-info/RECORD
