Metadata-Version: 2.1
Name: config-library
Version: 0.18.1
Summary: utility library to find and load configuration files
Home-page: https://github.com/utility-libraries/configlib-py
Author: PlayerG9
License: MIT
Project-URL: Organisation Github, https://github.com/utility-libraries
Project-URL: Homepage, https://github.com/utility-libraries/configlib-py/
Project-URL: Documentation, https://utility-libraries.github.io/configlib-py/
Project-URL: Bug Tracker, https://github.com/utility-libraries/configlib-py/issues
Classifier: Intended Audience :: Developers
Classifier: License :: OSI Approved :: MIT License
Classifier: Natural Language :: English
Classifier: Operating System :: OS Independent
Classifier: Programming Language :: Python :: 3
Classifier: Programming Language :: Python :: 3 :: Only
Classifier: Programming Language :: Python :: 3.7
Classifier: Programming Language :: Python :: 3.8
Classifier: Programming Language :: Python :: 3.9
Classifier: Programming Language :: Python :: 3.10
Classifier: Programming Language :: Python :: 3.11
Classifier: Programming Language :: Python :: 3.12
Classifier: Programming Language :: Python :: 3.13
Classifier: Topic :: Utilities
Requires-Python: >=3.5
License-File: LICENSE
Provides-Extra: all
Requires-Dist: pydantic ; extra == 'all'
Requires-Dist: pyyaml ; extra == 'all'
Requires-Dist: json-five ; extra == 'all'
Requires-Dist: python-dotenv ; extra == 'all'
Requires-Dist: toml ; (python_version < "3.11") and extra == 'all'
Provides-Extra: dotenv
Requires-Dist: python-dotenv ; extra == 'dotenv'
Provides-Extra: json5
Requires-Dist: json-five ; extra == 'json5'
Provides-Extra: toml
Requires-Dist: toml ; (python_version < "3.11") and extra == 'toml'
Provides-Extra: validation
Requires-Dist: pydantic ; extra == 'validation'
Provides-Extra: yaml
Requires-Dist: pyyaml ; extra == 'yaml'
